flagdataset/__init__.py
flagdataset/baai_config.py
flagdataset/baai_download.py
flagdataset/baai_download_custom.py
flagdataset/baai_downloader.py
flagdataset/baai_downloader_custom.py
flagdataset/baai_environment.py
flagdataset/baai_meta.py
flagdataset/baai_proc.py
flagdataset/baai_uploader.py
flagdataset/cmd/__init__.py
flagdataset/cmd/run_option.py
flagdataset/helper/__init__.py
flagdataset/helper/baai_jwtsign.py
flagdataset/helper/baai_logger.py
flagdataset/helper/baai_login.py
flagdataset/helper/baai_merge.py
flagdataset/helper/baai_pbar.py
flagdataset/helper/baai_print.py
flagdataset/helper/baai_read.py
flagdataset/helper/baai_requests.py
flagdataset/helper/baai_update.py
flagdataset/process/__init__.py
flagdataset/process/curobot2train_format.py
flagdataset/process/data_utils/__init__.py
flagdataset/process/data_utils/action_token/action_chunk_to_fast_token.py
flagdataset/process/data_utils/action_token/fast/README.md
flagdataset/process/data_utils/action_token/fast/gitattributes
flagdataset/process/data_utils/action_token/fast/processing_action_tokenizer.py
flagdataset/process/data_utils/action_token/fast/processor_config.json
flagdataset/process/data_utils/action_token/fast/special_tokens_map.json
flagdataset/process/data_utils/action_token/fast/tokenizer.json
flagdataset/process/data_utils/action_token/fast/tokenizer_config.json
flagdataset/process/data_utils/pose_transform.py
flagdataset/process/handle.py
flagdataset/process/merge_in_nas.py
flagdataset_eai-1.1.14.dist-info/METADATA
flagdataset_eai-1.1.14.dist-info/WHEEL
flagdataset_eai-1.1.14.dist-info/entry_points.txt
flagdataset_eai-1.1.14.dist-info/RECORD
