Metadata-Version: 2.3
Name: flagdataset-eai
Version: 1.1.14
Summary: 
License: MIT
Author: shihongguang
Author-email: hgshi@baai.ac.cn
Requires-Python: >=3.10,<3.13
Classifier: License :: OSI Approved :: MIT License
Classifier: Programming Language :: Python :: 3
Classifier: Programming Language :: Python :: 3.10
Classifier: Programming Language :: Python :: 3.11
Classifier: Programming Language :: Python :: 3.12
Requires-Dist: fastparquet (>=2024.11.0,<2025.0.0)
Requires-Dist: msgpack (>=1.1.1,<2.0.0)
Requires-Dist: numpy (==1.26.0)
Requires-Dist: opencv-python (>=4.6.0,<5.0.0)
Requires-Dist: pandas (==1.5.3)
Requires-Dist: psutil (>=7.1.0,<8.0.0)
Requires-Dist: pyarrow (>=22.0.0,<23.0.0)
Requires-Dist: pyjwt (>=2.10.1,<3.0.0)
Requires-Dist: requests (>=2.32.3,<3.0.0)
Requires-Dist: scikit-learn (==1.7.2)
Requires-Dist: tqdm (>=4.67.1,<5.0.0)
Requires-Dist: transformers (>=4.57.1,<5.0.0)
